dictionary/__init__.py
dictionary/dictionary.py
Emre_s_Dictionary-2.0.0.dist-info/METADATA
Emre_s_Dictionary-2.0.0.dist-info/WHEEL
Emre_s_Dictionary-2.0.0.dist-info/top_level.txt
Emre_s_Dictionary-2.0.0.dist-info/RECORD
