Metadata-Version: 2.1
Name: Emre-s-Dictionary
Version: 2.0.0
Summary: UNKNOWN
Author: Muhammed Emre YILDIZ
License: UNKNOWN
Platform: UNKNOWN
Requires-Python: >=3.8
Requires-Dist: requests (>=2.23.0)
